ordr/__init__.py
ordr-0.0.1.dist-info/LICENSE.txt
ordr-0.0.1.dist-info/METADATA
ordr-0.0.1.dist-info/WHEEL
ordr-0.0.1.dist-info/top_level.txt
ordr-0.0.1.dist-info/RECORD
